setup.py
blended_twitter_cards.egg-info/PKG-INFO
blended_twitter_cards.egg-info/SOURCES.txt
blended_twitter_cards.egg-info/dependency_links.txt
blended_twitter_cards.egg-info/not-zip-safe
blended_twitter_cards.egg-info/requires.txt
blended_twitter_cards.egg-info/top_level.txt
twitter_cards/__init__.py